{"commitInfo":{"timestamp":1772764827913,"operation":"CREATE OR REPLACE TABLE AS SELECT","operationParameters":{"isManaged":"false","description":null,"partitionBy":"[]","properties":"{}"},"readVersion":0,"isolationLevel":"Serializable","isBlindAppend":false,"operationMetrics":{"numFiles":"1","numOutputRows":"295","numOutputBytes":"13647"},"engineInfo":"Apache-Spark/3.5.5 Delta-Lake/3.0.0","txnId":"8737a77f-3782-4637-b8b3-abd90e93d6bc"}}
{"add":{"path":"part-00000-df28248a-a0a4-41e9-99b7-7729d79d41fc-c000.snappy.parquet","partitionValues":{},"size":13647,"modificationTime":1772764822796,"dataChange":true,"stats":"{\"numRecords\":295,\"minValues\":{\"ProductID\":680,\"ProductDesc\":\"AWC Logo Cap\",\"ProductNumber\":\"BB-7421\",\"Color\":\"Black\",\"SafetyStockLevel\":4,\"ReorderPoint\":3,\"Size\":\"38\",\"SizeUnitMeasureCode\":\"CM \",\"WeightUnitMeasureCode\":\"G  \",\"StandardCost\":0.86,\"ListPrice\":2.29,\"Weight\":2.12,\"ProductCategoryName\":\"Accessories\",\"ProductSubCategoryName\":\"Bib-Shorts\",\"loaded_at\":\"2026-03-06T02:40:18.024Z\"},\"maxValues\":{\"ProductID\":999,\"ProductDesc\":\"Women's Tights, S\",\"ProductNumber\":\"WB-H098\",\"Color\":\"Yellow\",\"SafetyStockLevel\":500,\"ReorderPoint\":375,\"Size\":\"XL\",\"SizeUnitMeasureCode\":\"CM \",\"WeightUnitMeasureCode\":\"LB \",\"StandardCost\":2171.29,\"ListPrice\":3578.27,\"Weight\":1050.00,\"ProductCategoryName\":\"Components\",\"ProductSubCategoryName\":\"Wheels\",\"loaded_at\":\"2026-03-06T02:40:18.024Z\"},\"nullCount\":{\"ProductID\":0,\"ProductDesc\":0,\"ProductNumber\":0,\"MakeFlag\":0,\"Color\":50,\"SafetyStockLevel\":0,\"ReorderPoint\":0,\"Size\":84,\"SizeUnitMeasureCode\":119,\"WeightUnitMeasureCode\":97,\"StandardCost\":0,\"ListPrice\":0,\"Weight\":97,\"ProductCategoryName\":182,\"ProductSubCategoryName\":0,\"loaded_at\":0}}"}}
{"remove":{"path":"part-00000-d8afc697-66bf-4c2c-a293-c4890b3b51ba-c000.snappy.parquet","deletionTimestamp":1772764827905,"dataChange":true,"extendedFileMetadata":true,"partitionValues":{},"size":13647}}
